auto_clicker/__init__.py
auto_clicker/file_0.py
auto_clicker-0.3.dist-info/LICENSE.txt
auto_clicker-0.3.dist-info/METADATA
auto_clicker-0.3.dist-info/WHEEL
auto_clicker-0.3.dist-info/top_level.txt
auto_clicker-0.3.dist-info/RECORD
