Metadata-Version: 2.1
Name: auto-clicker
Version: 0.3
Summary: You can search for images on your screen and then click, hover or press them.
Home-page: https://github.com/Warfare03/auto_clicker
Author: Finn Pfaff
Author-email: pfaff_finn@yahoo.com
License: UNKNOWN
Platform: UNKNOWN
Classifier: Programming Language :: Python :: 3
Classifier: License :: OSI Approved :: MIT License
Classifier: Operating System :: OS Independent
Requires-Python: >=3.6
